openbakery/__init__.py
openbakery/__main__.py
openbakery/_version.py
openbakery/axes_pb2.py
openbakery/callable.py
openbakery/checkrunner.py
openbakery/cli.py
openbakery/codetesting.py
openbakery/configuration.py
openbakery/constants.py
openbakery/designers_pb2.py
openbakery/errors.py
openbakery/fonts_profile.py
openbakery/fonts_public_pb2.py
openbakery/glyphdata.py
openbakery/message.py
openbakery/multiproc.py
openbakery/profile.py
openbakery/section.py
openbakery/status.py
openbakery/utils.py
openbakery/commands/__init__.py
openbakery/commands/build_contributors.py
openbakery/commands/check_profile.py
openbakery/commands/generate_glyphdata.py
openbakery/data/openbakery-microsoft-vendorlist.cache
openbakery/data/googlefonts/abbreviations_familyname_exceptions.txt
openbakery/data/googlefonts/camelcased_familyname_exceptions.txt
openbakery/data/googlefonts/reserved_font_name_exceptions.txt
openbakery/profiles/__init__.py
openbakery/profiles/adobefonts.py
openbakery/profiles/cff.py
openbakery/profiles/cmap.py
openbakery/profiles/dsig.py
openbakery/profiles/fontbureau.py
openbakery/profiles/fontval.py
openbakery/profiles/fontwerk.py
openbakery/profiles/fvar.py
openbakery/profiles/gdef.py
openbakery/profiles/glyf.py
openbakery/profiles/googlefonts.py
openbakery/profiles/googlefonts_conditions.py
openbakery/profiles/gpos.py
openbakery/profiles/head.py
openbakery/profiles/hhea.py
openbakery/profiles/iso15008.py
openbakery/profiles/kern.py
openbakery/profiles/layout.py
openbakery/profiles/loca.py
openbakery/profiles/name.py
openbakery/profiles/notofonts.py
openbakery/profiles/opentype.py
openbakery/profiles/os2.py
openbakery/profiles/outline.py
openbakery/profiles/post.py
openbakery/profiles/proposals.py
openbakery/profiles/shaping.py
openbakery/profiles/shared_conditions.py
openbakery/profiles/stat.py
openbakery/profiles/ufo_sources.py
openbakery/profiles/universal.py
openbakery/reporters/__init__.py
openbakery/reporters/badge.py
openbakery/reporters/ghmarkdown.py
openbakery-0.1.0.dist-info/AUTHORS.txt
openbakery-0.1.0.dist-info/LICENSE.txt
openbakery-0.1.0.dist-info/METADATA
openbakery-0.1.0.dist-info/WHEEL
openbakery-0.1.0.dist-info/entry_points.txt
openbakery-0.1.0.dist-info/top_level.txt
openbakery-0.1.0.dist-info/RECORD
