Metadata-Version: 2.1
Name: openbakery
Version: 0.1.0
Summary: A font quality assurance tool for everyone
Home-page: https://github.com/miguelsousa/openbakery/
Author: OpenBakery authors and contributors: Dave Crossland, Felipe Sanches, Lasse Fister, Marc Foley, Nikolaus Waxweiler, Chris Simpkins, Jens Kutilek, Vitaly Volkov, Simon Cozens, Miguel Sousa
Author-email: miguel.sousa@adobe.com
Classifier: Environment :: Console
Classifier: Intended Audience :: Developers
Classifier: License :: OSI Approved :: Apache Software License
Classifier: Operating System :: OS Independent
Classifier: Programming Language :: Python :: 3
Classifier: Programming Language :: Python :: 3.8
Classifier: Programming Language :: Python :: 3 :: Only
Requires-Python: >=3.8
License-File: LICENSE.txt
License-File: AUTHORS.txt
Requires-Dist: fontTools (>=4.39.0)
Requires-Dist: freetype-py (!=2.4.0)
Requires-Dist: munkres
Requires-Dist: opentypespec
Requires-Dist: opentype-sanitizer (>=7.1.9)
Requires-Dist: PyYAML
Requires-Dist: toml
Requires-Dist: cmarkgfm
Requires-Dist: rich
Requires-Dist: packaging
Requires-Dist: pip-api
Requires-Dist: requests
Requires-Dist: beziers (>=0.5.0)
Requires-Dist: collidoscope (>=0.5.2)
Requires-Dist: stringbrewer
Requires-Dist: ufo2ft (>=2.25.2)
Requires-Dist: vharfbuzz (>=0.2.0)
Provides-Extra: all
Requires-Dist: defcon ; extra == 'all'
Requires-Dist: axisregistry (>=0.3.0) ; extra == 'all'
Requires-Dist: ufolint ; extra == 'all'
Requires-Dist: fontTools[lxml,unicode] (>=4.39.0) ; extra == 'all'
Requires-Dist: ufo2ft (>=2.25.2) ; extra == 'all'
Requires-Dist: lxml ; extra == 'all'
Requires-Dist: beautifulsoup4 ; extra == 'all'
Requires-Dist: font-v ; extra == 'all'
Requires-Dist: fontTools[ufo] (>=4.39.0) ; extra == 'all'
Requires-Dist: gflanguages (>=0.3.0) ; extra == 'all'
Requires-Dist: protobuf (<4,>=3.7.0) ; extra == 'all'
Requires-Dist: dehinter (>=3.1.0) ; extra == 'all'
Requires-Dist: glyphsets (>=0.5.0) ; extra == 'all'
Provides-Extra: docs
Provides-Extra: fontval
Requires-Dist: lxml ; extra == 'fontval'
Provides-Extra: googlefonts
Requires-Dist: axisregistry (>=0.3.0) ; extra == 'googlefonts'
Requires-Dist: beautifulsoup4 ; extra == 'googlefonts'
Requires-Dist: dehinter (>=3.1.0) ; extra == 'googlefonts'
Requires-Dist: font-v ; extra == 'googlefonts'
Requires-Dist: fontTools[lxml,unicode] (>=4.39.0) ; extra == 'googlefonts'
Requires-Dist: gflanguages (>=0.3.0) ; extra == 'googlefonts'
Requires-Dist: glyphsets (>=0.5.0) ; extra == 'googlefonts'
Requires-Dist: protobuf (<4,>=3.7.0) ; extra == 'googlefonts'
Requires-Dist: defcon ; extra == 'googlefonts'
Requires-Dist: fontTools[ufo] (>=4.39.0) ; extra == 'googlefonts'
Requires-Dist: ufo2ft (>=2.25.2) ; extra == 'googlefonts'
Requires-Dist: ufolint ; extra == 'googlefonts'
Provides-Extra: ufo-sources
Requires-Dist: defcon ; extra == 'ufo-sources'
Requires-Dist: fontTools[ufo] (>=4.39.0) ; extra == 'ufo-sources'
Requires-Dist: ufo2ft (>=2.25.2) ; extra == 'ufo-sources'
Requires-Dist: ufolint ; extra == 'ufo-sources'
